<annotation>
	<folder></folder>
	<filename>Bitaniya_04_07_21_back_372_png.rf.9405bb61581192fd93391f1cc30dac28.jpg</filename>
	<path>Bitaniya_04_07_21_back_372_png.rf.9405bb61581192fd93391f1cc30dac28.jpg</path>
	<source>
		<database>roboflow.ai</database>
	</source>
	<size>
		<width>2560</width>
		<height>1920</height>
		<depth>3</depth>
	</size>
	<segmented>0</segmented>
	<object>
		<name>protozoa</name>
		<pose>Unspecified</pose>
		<truncated>0</truncated>
		<difficult>0</difficult>
		<occluded>0</occluded>
		<bndbox>
			<xmin>539</xmin>
			<xmax>1364</xmax>
			<ymin>604</ymin>
			<ymax>1453</ymax>
		</bndbox>
	</object>
	<object>
		<name>protozoa</name>
		<pose>Unspecified</pose>
		<truncated>0</truncated>
		<difficult>0</difficult>
		<occluded>0</occluded>
		<bndbox>
			<xmin>1299</xmin>
			<xmax>2239</xmax>
			<ymin>836</ymin>
			<ymax>1605</ymax>
		</bndbox>
	</object>
</annotation>
