<annotation>
	<folder></folder>
	<filename>Bitaniya_15_08_21_back_1434_png.rf.729c78aaa7529cfe3300ea163e8358dd.jpg</filename>
	<path>Bitaniya_15_08_21_back_1434_png.rf.729c78aaa7529cfe3300ea163e8358dd.jpg</path>
	<source>
		<database>roboflow.ai</database>
	</source>
	<size>
		<width>2560</width>
		<height>1920</height>
		<depth>3</depth>
	</size>
	<segmented>0</segmented>
	<object>
		<name>filament</name>
		<pose>Unspecified</pose>
		<truncated>0</truncated>
		<difficult>0</difficult>
		<occluded>0</occluded>
		<bndbox>
			<xmin>916</xmin>
			<xmax>1681</xmax>
			<ymin>1</ymin>
			<ymax>1609</ymax>
		</bndbox>
	</object>
</annotation>
