<annotation>
	<folder></folder>
	<filename>Hasolelim_11_07_21_back_1055_png.rf.21cc1aa612ec7fc2dcdc03cce64631e5.jpg</filename>
	<path>Hasolelim_11_07_21_back_1055_png.rf.21cc1aa612ec7fc2dcdc03cce64631e5.jpg</path>
	<source>
		<database>roboflow.ai</database>
	</source>
	<size>
		<width>2560</width>
		<height>1920</height>
		<depth>3</depth>
	</size>
	<segmented>0</segmented>
	<object>
		<name>filament</name>
		<pose>Unspecified</pose>
		<truncated>0</truncated>
		<difficult>0</difficult>
		<occluded>0</occluded>
		<bndbox>
			<xmin>954</xmin>
			<xmax>1362</xmax>
			<ymin>451</ymin>
			<ymax>861</ymax>
		</bndbox>
	</object>
</annotation>
